_speedoc.py
speedoc-0.2.dist-info/LICENSE.txt
speedoc-0.2.dist-info/METADATA
speedoc-0.2.dist-info/WHEEL
speedoc-0.2.dist-info/entry_points.txt
speedoc-0.2.dist-info/top_level.txt
speedoc-0.2.dist-info/RECORD
