Metadata-Version: 2.1
Name: speedoc
Version: 0.2
Summary: sphinx meets pydoc.
Home-page: https://github.com/anntzer/speedoc
Author: Antony Lee
License: MIT
Platform: UNKNOWN
Classifier: Development Status :: 4 - Beta
Classifier: Environment :: Console
Classifier: Intended Audience :: Developers
Classifier: License :: OSI Approved :: MIT License
Classifier: Operating System :: Unix
Classifier: Programming Language :: Python :: 3
Classifier: Topic :: Documentation
Requires-Python: >=3
Requires-Dist: sphinx (>=1.5)
